aurum_os_base/__init__.py
aurum_os_base/check_aurum_os_version.py
aurum_os_base/crypt.py
aurum_os_base/file_system_operations.py
aurum_os_base/networking_operations.py
aurum_os_base/process_management.py
aurum_os_base/system_information.py
aurum_os_base-0.1.1.dist-info/LICENSE
aurum_os_base-0.1.1.dist-info/METADATA
aurum_os_base-0.1.1.dist-info/WHEEL
aurum_os_base-0.1.1.dist-info/RECORD
