Metadata-Version: 2.1
Name: aurum-os-base
Version: 0.1.1
Summary: A base package for the aurumOS
Home-page: https://alcheon-llc.github.io/apkg-repo/aurum-os-base/
Author: lxchn1v1
Author-email: flat.assembly@gmail.com
Requires-Python: >=3.10,<4.0
Classifier: Programming Language :: Python :: 3
Classifier: Programming Language :: Python :: 3.10
Classifier: Programming Language :: Python :: 3.11
Requires-Dist: cryptography (>=3.4.8,<4.0.0)
Requires-Dist: msgpack (>=1.0.2,<2.0.0)
Requires-Dist: requests (>=2.26.0,<3.0.0)
Project-URL: Repository, https://github.com/alcheon-llc/aurum-os-base
